Metadata-Version: 2.4
Name: ai-code-review
Version: 4.0.1
Summary: AI code review tool that works with any language model provider. It detects issues in GitHub pull requests or local changes—instantly, reliably, and without vendor lock-in.
License: MIT
License-File: LICENSE
Keywords: static code analysis,code review,code quality,ai,coding,assistant,llm,github,automation,devops,developer tools,github actions,workflows,github-actions,git,pull-request,jira,linear,gitlab,ci-cd,static analysis
Author: Nayjest
Author-email: mail@vitaliy.in
Requires-Python: >=3.11,<4.0
Classifier: Development Status :: 5 - Production/Stable
Classifier: Environment :: Console
Classifier: Intended Audience :: Developers
Classifier: Intended Audience :: System Administrators
Classifier: License :: OSI Approved :: MIT License
Classifier: Operating System :: OS Independent
Classifier: Programming Language :: Python :: 3
Classifier: Programming Language :: Python :: 3.11
Classifier: Programming Language :: Python :: 3.12
Classifier: Programming Language :: Python :: 3.13
Classifier: Programming Language :: Python :: 3.14
Classifier: Topic :: Scientific/Engineering :: Artificial Intelligence
Classifier: Topic :: Software Development
Classifier: Topic :: Software Development :: Bug Tracking
Classifier: Topic :: Software Development :: Quality Assurance
Classifier: Topic :: Software Development :: Testing
Classifier: Topic :: Software Development :: Version Control :: Git
Requires-Dist: GitPython (>=3.1.44,<4.0.0)
Requires-Dist: ai-microcore (>=5.0.0,<5.1.0)
Requires-Dist: anthropic (>=0.57.1,<1)
Requires-Dist: fastcore (>=1.11.3,<1.12.0)
Requires-Dist: ghapi (>=1.0.8,<1.1.0)
Requires-Dist: google-genai (>=1.56.0,<1.57.0)
Requires-Dist: jira (>=3.10.5,<4.0.0)
Requires-Dist: pydantic (>=2.12.5,<3.0.0)
Requires-Dist: typer (>=0.16.0,<0.22)
Requires-Dist: unidiff (>=0.7.5,<0.8.0)
Project-URL: Bug Tracker, https://github.com/Nayjest/Gito/issues
Project-URL: Documentation, https://github.com/Nayjest/Gito#readme
Project-URL: Homepage, https://github.com/Nayjest/Gito
Project-URL: Repository, https://github.com/Nayjest/Gito
